schiller/__init__.py
schiller/datetime.py
schiller/ecg_generator.py
schiller/fs_util.py
schiller/io.py
schiller/main.py
schiller/smb_file_transfer.py
schiller-0.3.1.dist-info/LICENSE
schiller-0.3.1.dist-info/METADATA
schiller-0.3.1.dist-info/WHEEL
schiller-0.3.1.dist-info/entry_points.txt
schiller-0.3.1.dist-info/top_level.txt
schiller-0.3.1.dist-info/RECORD
