Metadata-Version: 2.1
Name: schiller
Version: 0.3.1
Summary: Python tools that can be used for other python projects
Home-page: https://schiller.ch
Author: Schiller AG
Author-email: your.name@schiller.ch
Classifier: Programming Language :: Python
Classifier: Programming Language :: Python :: 3.10
Requires-Python: >=3.8
License-File: LICENSE
Requires-Dist: pysmb
Provides-Extra: ecg_gen
Requires-Dist: numpy ; extra == 'ecg_gen'
